starSwimmer/Swimmer.py
starSwimmer/__init__.py
starSwimmer-0.0.2.dist-info/METADATA
starSwimmer-0.0.2.dist-info/WHEEL
starSwimmer-0.0.2.dist-info/top_level.txt
starSwimmer-0.0.2.dist-info/RECORD
