Metadata-Version: 2.1
Name: starSwimmer
Version: 0.0.2
Summary: 3D Star Swimmer package
Author: Alireza Astane
Author-email: <apoorhass@gmail.com>
Keywords: Swimmer
Classifier: Development Status :: 3 - Alpha
Classifier: Intended Audience :: Education
Classifier: Programming Language :: Python :: 2
Classifier: Programming Language :: Python :: 3
Classifier: Operating System :: MacOS :: MacOS X
Classifier: Operating System :: Microsoft :: Windows
